yaml_plotter/__init__.py
yaml_plotter/chart_2D.py
yaml_plotter/copy_example.py
yaml_plotter/example.yml
yaml_plotter/integrity_check.py
yaml_plotter/real_time_watcher.py
yaml_plotter-0.2.0.dist-info/LICENSE
yaml_plotter-0.2.0.dist-info/METADATA
yaml_plotter-0.2.0.dist-info/WHEEL
yaml_plotter-0.2.0.dist-info/entry_points.txt
yaml_plotter-0.2.0.dist-info/top_level.txt
yaml_plotter-0.2.0.dist-info/RECORD
